MANIFEST.in
setup.cfg
setup.py
RumAlchemy.egg-info/PKG-INFO
RumAlchemy.egg-info/SOURCES.txt
RumAlchemy.egg-info/dependency_links.txt
RumAlchemy.egg-info/entry_points.txt
RumAlchemy.egg-info/not-zip-safe
RumAlchemy.egg-info/requires.txt
RumAlchemy.egg-info/top_level.txt
rumalchemy/__init__.py
rumalchemy/command.py
rumalchemy/controller.py
rumalchemy/fieldfactory.py
rumalchemy/json.py
rumalchemy/query.py
rumalchemy/repository.py
rumalchemy/sqlsoup.py
rumalchemy/util.py
rumalchemy/tests/__init__.py
rumalchemy/tests/model.py
rumalchemy/tests/model2.py
rumalchemy/tests/test_fieldfactory.py
rumalchemy/tests/test_query.py
rumalchemy/tests/test_repository.py