Metadata-Version: 1.0
Name: RumAlchemy
Version: 0.4dev-20110726
Summary: RESTful web interface generator for SQLAlchemy mapped classes using rum and ToscaWidgets
Home-page: http://python-rum.org/
Author: Alberto Valverde Gonzalez, Michael Brickenstein
Author-email: info@python-rum.org
License: MIT
Keywords: toscawidgets sqlalchemy rum
Platform: UNKNOWN
